[
  {
    "RuleCode": "BCR-001",
    "RuleName": "基地建蔽率檢討",
    "Category": "基地",
    "CheckType": "Manual",
    "Parameter": "",
    "Operator": "",
    "Value": "",
    "Description": "【設計合規】依據建築技術規則設計施工編第 25 條，建築基地之建蔽率（建築面積佔基地面積比例）不得大於都市計畫規定之限制值。建蔽率 = 建築面積 / 基地面積。",
    "Perspective": "Architect",
    "LawArticle": "§25",
    "LawChapter": "第一章 基地與綠建築",
    "ApplicableCategories": ["OST_ProjectInformation"]
  },
  {
    "RuleCode": "BCR-002",
    "RuleName": "基地容積率檢討",
    "Category": "基地",
    "CheckType": "Manual",
    "Parameter": "",
    "Operator": "",
    "Value": "",
    "Description": "【設計合規】依據建築技術規則設計施工編第 161 條，建築基地之容積率（總樓地板面積佔基地面積比例）不得大於都市計畫規定之限制值。容積率 = 總樓地板面積 / 基地面積。",
    "Perspective": "Architect",
    "LawArticle": "§161",
    "LawChapter": "第八章 容積管制",
    "ApplicableCategories": ["OST_ProjectInformation"]
  },
  {
    "RuleCode": "BCR-003",
    "RuleName": "綠建築綠覆率檢討",
    "Category": "基地",
    "CheckType": "Manual",
    "Parameter": "",
    "Operator": "",
    "Value": "",
    "Description": "【設計合規】依據設計施工編第十七章，特定規模以上之建築物應進行綠建築基準檢討，且基地綠覆率（綠地面積與人工地盤綠化折算面積總和佔空地面積之比例）應達規定標準。",
    "Perspective": "Architect",
    "LawArticle": "§十七章",
    "LawChapter": "第十七章 綠建築",
    "ApplicableCategories": ["OST_ProjectInformation"]
  },
  {
    "RuleCode": "BCR-004",
    "RuleName": "面臨道路寬度限制",
    "Category": "基地",
    "CheckType": "Manual",
    "Parameter": "",
    "Operator": "",
    "Value": "",
    "Description": "【設計合規】依據設計施工編第 2 條，建築基地應面臨指定之道路，其面寬不得小於法規規定之最小寬度。建築基地無直達道路者，不得建築。",
    "Perspective": "Architect",
    "LawArticle": "§2",
    "LawChapter": "第一章 基地與綠建築",
    "ApplicableCategories": ["OST_ProjectInformation"]
  },
  {
    "RuleCode": "BCR-005",
    "RuleName": "基地防災通道寬度",
    "Category": "基地",
    "CheckType": "Manual",
    "Parameter": "",
    "Operator": "",
    "Value": "",
    "Description": "【設計合規】依據設計施工編第 2-1 條，高層建築物或特定規模建築物，基地內應留設寬度達 4m 以上之防火避難因應通道，以供消防車輛通行與避難操作。",
    "Perspective": "Architect",
    "LawArticle": "§2-1",
    "LawChapter": "第一章 基地與綠建築",
    "ApplicableCategories": ["OST_ProjectInformation"]
  },
  {
    "RuleCode": "BCR-011",
    "RuleName": "住宅居室面積限制",
    "Category": "其他",
    "CheckType": "Manual",
    "Parameter": "",
    "Operator": "",
    "Value": "",
    "Description": "【設計合規】依據設計施工編第 32 條，住宅之主臥室面積不得小於 10 平方公尺，其他居室面積不得小於 6 平方公尺，以保障基本居住品質。",
    "Perspective": "Architect",
    "LawArticle": "§32",
    "LawChapter": "第二章 第一節 居室與淨高",
    "ApplicableCategories": ["OST_Rooms"]
  },
  {
    "RuleCode": "BCR-012",
    "RuleName": "居室天花板淨高度",
    "Category": "高度",
    "CheckType": "Auto",
    "Parameter": "淨高",
    "Operator": ">=",
    "Value": "2100",
    "Description": "【雙端關注】依據設計施工編第 32 條，居室淨高度不得小於 2.1m；若有梁下天花，其平均高度不得小於 2.3m。天花板上設有空調或風管者，其淨高亦須符合限制。",
    "Perspective": "Both",
    "LawArticle": "§32",
    "LawChapter": "第二章 第一節 居室與淨高",
    "ApplicableCategories": ["OST_Rooms"]
  },
  {
    "RuleCode": "BCR-013",
    "RuleName": "居室採光通風面積",
    "Category": "其他",
    "CheckType": "Manual",
    "Parameter": "",
    "Operator": "",
    "Value": "",
    "Description": "【設計合規】依據設計施工編第 43 條，學校、幼兒園、住宅等居室之有效採光面積不得小於該層樓地板面積之 1/8。有效通風面積不得小於 1/10。",
    "Perspective": "Architect",
    "LawArticle": "§43",
    "LawChapter": "第二章 第二節 採光與通風",
    "ApplicableCategories": ["OST_Rooms", "OST_Windows"]
  },
  {
    "RuleCode": "BCR-014",
    "RuleName": "廁所衛浴通風設備",
    "Category": "其他",
    "CheckType": "Manual",
    "Parameter": "",
    "Operator": "",
    "Value": "",
    "Description": "【設計合規】依據設計施工編第 44 條，建築物之廁所、浴室應設有窗戶直接面向戶外或安裝機械排風通風設備，確保空氣流通與衛生健康。",
    "Perspective": "Architect",
    "LawArticle": "§44",
    "LawChapter": "第二章 第二節 採光與通風",
    "ApplicableCategories": ["OST_Rooms"]
  },
  {
    "RuleCode": "BCR-015",
    "RuleName": "露台陽台欄杆高度",
    "Category": "其他",
    "CheckType": "Auto",
    "Parameter": "高度",
    "Operator": ">=",
    "Value": "1100",
    "Description": "【雙端關注】依據設計施工編第 38 條，設置於露臺、陽臺、室外走廊、平屋頂等處之欄杆扶手高度，不得小於 1.10 公尺；十層以上者，不得小於 1.20 公尺。欄杆不得設有可供直徑 10 公分物體穿越之鏤空，且不得設置水平橫條。",
    "Perspective": "Both",
    "LawArticle": "§38",
    "LawChapter": "第二章 第三節 天台與防墜",
    "ApplicableCategories": ["OST_Walls", "OST_Railings"]
  },
  {
    "RuleCode": "BCR-021",
    "RuleName": "建築物高度限制檢討",
    "Category": "高度",
    "CheckType": "Manual",
    "Parameter": "",
    "Operator": "",
    "Value": "",
    "Description": "【設計合規】依據設計施工編第 164 條，建築物高度不得大於路心投影比例限制、後院深度比例限制及日照陰影等規定，以維護都市空間日照與視覺品質。",
    "Perspective": "Architect",
    "LawArticle": "§164",
    "LawChapter": "第八章 建築物高度管制",
    "ApplicableCategories": ["OST_Levels"]
  },
  {
    "RuleCode": "BCR-022",
    "RuleName": "冬至有效日照檢討",
    "Category": "高度",
    "CheckType": "Manual",
    "Parameter": "",
    "Operator": "",
    "Value": "",
    "Description": "【設計合規】依據設計施工編第 23 條，住宅區新建建築物應檢討冬至日照陰影，確保鄰地冬至日具有法規規定之最小有效日照時間（如一小時以上）。",
    "Perspective": "Architect",
    "LawArticle": "§23",
    "LawChapter": "第一章 基地與綠建築",
    "ApplicableCategories": ["OST_ProjectInformation"]
  },
  {
    "RuleCode": "BCR-023",
    "RuleName": "後院深度與相鄰限制",
    "Category": "高度",
    "CheckType": "Manual",
    "Parameter": "",
    "Operator": "",
    "Value": "",
    "Description": "【設計合規】依據設計施工編第 26 條，建築物後院深度應符合規定，且防火間距寬度應符合最小邊界限制，防止火災蔓延至相鄰基地。",
    "Perspective": "Architect",
    "LawArticle": "§26",
    "LawChapter": "第一章 基地與綠建築",
    "ApplicableCategories": ["OST_ProjectInformation"]
  },
  {
    "RuleCode": "BCR-033",
    "RuleName": "住宅走廊寬度檢討",
    "Category": "走廊",
    "CheckType": "Auto",
    "Parameter": "寬度",
    "Operator": ">=",
    "Value": "1200",
    "Description": "【雙端關注】依據建築技術規則設計施工編第 92 條，走廊淨寬度單側有居室者不得小於 1.20 公尺 (1200mm)，雙側有居室者不得小於 1.60 公尺 (1600mm)；其他非住宅類建築有更寬之限制。",
    "Perspective": "Both",
    "LawArticle": "§92",
    "LawChapter": "第四章 第二節 避難走廊",
    "ApplicableCategories": ["OST_Rooms"]
  },
  {
    "RuleCode": "BCR-034",
    "RuleName": "樓梯級高級深安全限制",
    "Category": "樓梯",
    "CheckType": "Auto",
    "Parameter": "最大級高",
    "Operator": "<=",
    "Value": "180",
    "Description": "【雙端關注】依據建築技術規則設計施工編第 33 條：\n1. 供公眾使用與安全避難梯：級高 <= 160mm，級深 >= 260mm，淨寬 >= 1200mm。\n2. 集合住宅與辦公大樓：級高 <= 180mm，級深 >= 240mm，淨寬 >= 1200mm。\n3. 其他住宅(透天)及常規樓梯：級高 <= 200mm，級深 >= 220mm，淨寬 >= 750mm。",
    "Perspective": "Both",
    "LawArticle": "§33",
    "LawChapter": "第二章 第五節 樓梯與安全梯",
    "ApplicableCategories": ["OST_Stairs"]
  },
  {
    "RuleCode": "BCR-035",
    "RuleName": "樓梯扶手與淨高檢討",
    "Category": "樓梯",
    "CheckType": "Manual",
    "Parameter": "",
    "Operator": "",
    "Value": "",
    "Description": "【雙端關注】依據設計施工編第 35、36 條，樓梯扶手高度應大於等於 75cm (大於三階者)，十層以上應大於 110cm；且樓梯淨高度（梯級鼻端至上方天花板或梁底之垂直距離）不得小於 1.9m。",
    "Perspective": "Both",
    "LawArticle": "§35",
    "LawChapter": "第二章 第五節 樓梯與安全梯",
    "ApplicableCategories": ["OST_Stairs", "OST_Railings"]
  },
  {
    "RuleCode": "BCR-036",
    "RuleName": "樓梯平台設置限制",
    "Category": "樓梯",
    "CheckType": "Manual",
    "Parameter": "",
    "Operator": "",
    "Value": "",
    "Description": "【雙端關注】依據設計施工編第 35 條，樓梯高度每超過 3m 應留設平台，且平台寬度不得小於該樓梯淨寬度，避免行走疲勞與跌落風險。",
    "Perspective": "Both",
    "LawArticle": "§35",
    "LawChapter": "第二章 第五節 樓梯與安全梯",
    "ApplicableCategories": ["OST_Stairs"]
  },
  {
    "RuleCode": "BCR-037",
    "RuleName": "樓梯淨寬度檢討",
    "Category": "樓梯",
    "CheckType": "Auto",
    "Parameter": "寬度",
    "Operator": ">=",
    "Value": "1200",
    "Description": "【設計合規】依據設計施工編第 33 條與第 33-1 條，樓梯淨寬度應符合各用途別之法定限制（如集合住宅為 1.2m 以上，公共建築為 1.4m 以上）。",
    "Perspective": "Both",
    "LawArticle": "§33-1",
    "LawChapter": "第二章 第五節 樓梯與安全梯",
    "ApplicableCategories": ["OST_Stairs"]
  },
  {
    "RuleCode": "BCR-038",
    "RuleName": "樓層高度檢討",
    "Category": "高度",
    "CheckType": "Auto",
    "Parameter": "高度",
    "Operator": ">=",
    "Value": "2600",
    "Description": "【設計合規】依據設計施工編第 33 條，居室最低高度或相鄰樓層高度差應大於等於 2.6m（居室最低要求）或依用途別之淨高設計限制。",
    "Perspective": "Architect",
    "LawArticle": "§33",
    "LawChapter": "第二章 第一節 居室與淨高",
    "ApplicableCategories": ["OST_Levels"]
  },
  {
    "RuleCode": "BCR-071",
    "RuleName": "主要構造防火時效",
    "Category": "防火",
    "CheckType": "Manual",
    "Parameter": "",
    "Operator": "",
    "Value": "",
    "Description": "【雙端關注】依據設計施工編第 70 條，主要構造（梁、柱、承重牆、外牆、樓地板、屋頂）之防火構造時效應符合法規規定。例如承重牆、柱、梁之防火時效通常要求 1.0 至 2.0 小時以上。",
    "Perspective": "Both",
    "LawArticle": "§70",
    "LawChapter": "第三章 第一節 防火構造",
    "ApplicableCategories": ["OST_Walls", "OST_Floors", "OST_StructuralColumns", "OST_StructuralFraming"]
  },
  {
    "RuleCode": "BCR-072",
    "RuleName": "防火區劃限制檢討",
    "Category": "防火",
    "CheckType": "Manual",
    "Parameter": "",
    "Operator": "",
    "Value": "",
    "Description": "【雙端關注】依據設計施工編第 79 條，建築物應依規定之樓地板面積及構造限制進行防火區劃配置（如以具一小時以上防火時效之牆壁、樓地板及防火門窗區劃，避免火災大範圍蔓延）。",
    "Perspective": "Both",
    "LawArticle": "§79",
    "LawChapter": "第三章 第三節 防火區劃",
    "ApplicableCategories": ["OST_Walls", "OST_Floors"]
  },
  {
    "RuleCode": "BCR-073",
    "RuleName": "管道間防火區劃限制",
    "Category": "防火",
    "CheckType": "Manual",
    "Parameter": "",
    "Operator": "",
    "Value": "",
    "Description": "【營造施工】依據設計施工編第 80 條，貫穿樓地板之管道間，應在每層樓板位置以不燃材料做防火區劃封塞（如防火泥、阻火圈），防止煙囪效應導致火煙跨樓層蔓延。",
    "Perspective": "Contractor",
    "LawArticle": "§80",
    "LawChapter": "第三章 第三節 防火區劃",
    "ApplicableCategories": ["OST_Floors"]
  },
  {
    "RuleCode": "BCR-074",
    "RuleName": "防火區劃面積檢討",
    "Category": "防火",
    "CheckType": "SemiAuto",
    "Parameter": "面積",
    "Operator": "<=",
    "Value": "1500",
    "Description": "【設計合規】依據設計施工編第 79 條，防火區劃之最大樓地板面積通常限制於 1500 平方公尺以內（有灑水設備可放寬為 3000 平方公尺）。",
    "Perspective": "Both",
    "LawArticle": "§79",
    "LawChapter": "第三章 第三節 防火區劃",
    "ApplicableCategories": ["OST_Rooms"]
  },
  {
    "RuleCode": "BCR-076",
    "RuleName": "安全梯避難門寬度檢討",
    "Category": "開口",
    "CheckType": "Auto",
    "Parameter": "寬度",
    "Operator": ">=",
    "Value": "900",
    "Description": "【雙端關注】避難安全梯之防火門/逃生門淨寬度不得小於 900mm (依據設計施工編第七十六條)。門扇開啟時不得阻礙安全走廊之避難流線寬度。",
    "Perspective": "Both",
    "LawArticle": "§76",
    "LawChapter": "第三章 第二節 避難門",
    "ApplicableCategories": ["OST_Doors"]
  },
  {
    "RuleCode": "BCR-077",
    "RuleName": "出入口門扇開啟方向",
    "Category": "開口",
    "CheckType": "SemiAuto",
    "Parameter": "開啟方向",
    "Operator": "==",
    "Value": "朝避難方向",
    "Description": "【雙端關注】依據設計施工編第 76 條，避難出入口門及防火門扇之開啟方向，應朝向避難逃生方向開啟，以利緊急疏散。",
    "Perspective": "Both",
    "LawArticle": "§76",
    "LawChapter": "第三章 第二節 避難門",
    "ApplicableCategories": ["OST_Doors"]
  },
  {
    "RuleCode": "BCR-085",
    "RuleName": "內部裝修耐燃材料檢討",
    "Category": "室內裝修",
    "CheckType": "Manual",
    "Parameter": "",
    "Operator": "",
    "Value": "",
    "Description": "【雙端關注】依據設計施工編第 88 條，建築物各居室、通道之天花板與牆面內部裝修材料，應具備規定之耐燃時效防焰等級（如耐燃一級、二級），以延緩火災蔓延速度。",
    "Perspective": "Both",
    "LawArticle": "§88",
    "LawChapter": "第三章 第四節 室內裝修",
    "ApplicableCategories": ["OST_Rooms"]
  },
  {
    "RuleCode": "BCR-090",
    "RuleName": "防火門防火時效檢討",
    "Category": "防火",
    "CheckType": "Auto",
    "Parameter": "防火時效",
    "Operator": ">=",
    "Value": "60",
    "Description": "【雙端關注】依據設計施工編第 76 條，安全梯與防火區劃之防火門防火時效應達到 1.0 小時 (60分鐘) 以上（即具備甲種防火門規格）。",
    "Perspective": "Both",
    "LawArticle": "§76",
    "LawChapter": "第三章 第二節 避難門",
    "ApplicableCategories": ["OST_Doors"]
  },
  {
    "RuleCode": "BCR-091",
    "RuleName": "避難層出入口寬度數量",
    "Category": "開口",
    "CheckType": "Manual",
    "Parameter": "",
    "Operator": "",
    "Value": "",
    "Description": "【設計合規】依據設計施工編第 90 條，避難層出入口之配置數量及個別淨寬度應符合規定，且總寬度應大於避難容納人數比例計算值，以確保緊急狀況下人流可快速疏散。",
    "Perspective": "Architect",
    "LawArticle": "§90",
    "LawChapter": "第四章 第一節 避難出口與樓梯",
    "ApplicableCategories": ["OST_Doors"]
  },
  {
    "RuleCode": "BCR-092",
    "RuleName": "避難層出入口淨寬",
    "Category": "開口",
    "CheckType": "Auto",
    "Parameter": "寬度",
    "Operator": ">=",
    "Value": "1200",
    "Description": "【設計合規】依據設計施工編第 90 條，避難層出入口（如大門、安全出口）之個別淨寬度不得小於 1.20 公尺 (1200mm)。",
    "Perspective": "Both",
    "LawArticle": "§90",
    "LawChapter": "第四章 第一節 避難出口與樓梯",
    "ApplicableCategories": ["OST_Doors"]
  },
  {
    "RuleCode": "BCR-093",
    "RuleName": "直通樓梯步行距離法規追蹤",
    "Category": "避難",
    "CheckType": "Manual",
    "Parameter": "",
    "Operator": "",
    "Value": "",
    "Description": "【設計合規】依據設計施工編第 93 條，自建築物避難層以外各部至直通樓梯之步行距離應在 30m 或 50m 限制內（高層或防火構造有不同放寬標準），確保短時間內可抵達樓梯間。",
    "Perspective": "Architect",
    "LawArticle": "§93",
    "LawChapter": "第四章 第一節 避難出口與樓梯",
    "ApplicableCategories": ["OST_Rooms"]
  },
  {
    "RuleCode": "BCR-094",
    "RuleName": "直通樓梯步行距離檢討",
    "Category": "避難",
    "CheckType": "Auto",
    "Parameter": "避難距離",
    "Operator": "<=",
    "Value": "30",
    "Description": "【雙端關注】依據設計施工編第 93 條，非防火構造之一般居室至直通樓梯之步行避難距離應在 30 公尺以下（若是防火構造可放寬為 50 公尺）。",
    "Perspective": "Both",
    "LawArticle": "§93",
    "LawChapter": "第四章 第一節 避難出口與樓梯",
    "ApplicableCategories": ["OST_Rooms"]
  },
  {
    "RuleCode": "BCR-095",
    "RuleName": "直通樓梯數量檢討",
    "Category": "避難",
    "CheckType": "Manual",
    "Parameter": "",
    "Operator": "",
    "Value": "",
    "Description": "【設計合規】依據設計施工編第 95 條，特定用途或特定樓地板面積、規模以上之樓層，應配置二座以上之直通樓梯通往避難層，以防單一樓梯被火煙阻斷。",
    "Perspective": "Architect",
    "LawArticle": "§95",
    "LawChapter": "第四章 第一節 避難出口與樓梯",
    "ApplicableCategories": ["OST_Stairs"]
  },
  {
    "RuleCode": "BCR-096",
    "RuleName": "安全梯構造檢討",
    "Category": "避難",
    "CheckType": "Manual",
    "Parameter": "",
    "Operator": "",
    "Value": "",
    "Description": "【設計合規】依據設計施工編第 96 條，直通樓梯之構造應依建築高度與用途配置為室內安全梯、戶外安全梯或特別安全梯，並配置防火門與排煙室。",
    "Perspective": "Architect",
    "LawArticle": "§96",
    "LawChapter": "第四章 第一節 避難出口與樓梯",
    "ApplicableCategories": ["OST_Stairs"]
  },
  {
    "RuleCode": "BCR-098",
    "RuleName": "屋頂避難平台配置",
    "Category": "避難",
    "CheckType": "Manual",
    "Parameter": "",
    "Operator": "",
    "Value": "",
    "Description": "【設計合規】依據設計施工編第 99 條，五層以上之特定用途建築物，應於屋頂設有避難平台，其面積應達規定比例且不得設障礙，以供直昇機救援或人員暫避。",
    "Perspective": "Architect",
    "LawArticle": "§99",
    "LawChapter": "第四章 第一節 避難出口與樓梯",
    "ApplicableCategories": ["OST_ProjectInformation"]
  },
  {
    "RuleCode": "BCR-099",
    "RuleName": "排煙設備設置檢討",
    "Category": "避難",
    "CheckType": "Manual",
    "Parameter": "",
    "Operator": "",
    "Value": "",
    "Description": "【雙端關注】依據設計施工編第 102 條，避難通道、直通樓梯、特別安全梯排煙室及特定房間應設置機械排煙或具備規定有效面積之自然排煙窗，防止嗆傷窒息。",
    "Perspective": "Both",
    "LawArticle": "§102",
    "LawChapter": "第四章 第三節 防煙排煙設備",
    "ApplicableCategories": ["OST_Windows", "OST_Rooms"]
  },
  {
    "RuleCode": "BCR-100",
    "RuleName": "緊急進口設置檢討",
    "Category": "開口",
    "CheckType": "Manual",
    "Parameter": "",
    "Operator": "",
    "Value": "",
    "Description": "【設計合規】依據設計施工編第 108 條，二層以上、十層以下之各樓層，應面臨道路或留設無礙消防活動之空地，並設置有效之緊急進口紅色三角形圓盤窗，以供消防員入內救援。",
    "Perspective": "Architect",
    "LawArticle": "§108",
    "LawChapter": "第四章 第四節 緊急進口",
    "ApplicableCategories": ["OST_Windows"]
  },
  {
    "RuleCode": "BCR-101",
    "RuleName": "避難步行距離檢討",
    "Category": "避難",
    "CheckType": "Auto",
    "Parameter": "",
    "Operator": "",
    "Value": "",
    "Description": "【雙端關注】利用 2D A* 路徑尋優演算法繞過牆與柱等障礙，計算房間最遠角落點至安全出口之「真實避難路線長度」，檢核是否符合法定 30m 限制。",
    "Perspective": "Both",
    "LawArticle": "§93",
    "LawChapter": "第四章 第一節 避難出口與樓梯",
    "ApplicableCategories": ["OST_Rooms"]
  },
  {
    "RuleCode": "BCR-102",
    "RuleName": "輪椅無障礙迴轉圓檢討",
    "Category": "無障礙",
    "CheckType": "Auto",
    "Parameter": "",
    "Operator": "",
    "Value": "",
    "Description": "【雙端關注】利用最大內切圓空間演算法，自動檢測無障礙廁所與空間內是否包含直徑 1.5m (1500mm) 的輪椅活動迴轉圓空間。",
    "Perspective": "Both",
    "LawArticle": "§170",
    "LawChapter": "第十章 無障礙建築物",
    "ApplicableCategories": ["OST_Rooms"]
  },
  {
    "RuleCode": "BCR-103",
    "RuleName": "梁下與管線結構淨高檢討",
    "Category": "高度",
    "CheckType": "Auto",
    "Parameter": "",
    "Operator": "",
    "Value": "",
    "Description": "【營造施工】實質空間碰撞檢測。利用 ReferenceIntersector 雷射在房間天花發射網格線，碰撞結構梁、板與風水管線，篩選出低於 2.1m 的實質施工衝突淨高區域。",
    "Perspective": "Contractor",
    "LawArticle": "§33",
    "LawChapter": "第二章 第一節 居室與淨高",
    "ApplicableCategories": ["OST_Rooms"]
  },
  {
    "RuleCode": "BCR-104",
    "RuleName": "機電穿梁牆套管遺漏檢討",
    "Category": "消防",
    "CheckType": "Auto",
    "Parameter": "",
    "Operator": "",
    "Value": "",
    "Description": "【營造施工】檢測穿越剪力牆、結構梁的機電管線（風管、水管、線槽）交接碰撞處，是否遺漏配置套管家族，以防現場洗洞破壞結構安全。",
    "Perspective": "Contractor",
    "LawArticle": "—",
    "LawChapter": "營造與施工安全",
    "ApplicableCategories": ["OST_PipeCurves"]
  },
  {
    "RuleCode": "BCR-105",
    "RuleName": "裝修參數幾何一致性檢討",
    "Category": "室內裝修",
    "CheckType": "Auto",
    "Parameter": "",
    "Operator": "",
    "Value": "",
    "Description": "【營造施工】料量與工法核對。比對 Room 的裝修參數（地磚/天花）與模型中實際建立的實體 Floor、Ceiling 的幾何材料是否相符，防止數量計算與施工錯誤。",
    "Perspective": "Contractor",
    "LawArticle": "—",
    "LawChapter": "營造與施工安全",
    "ApplicableCategories": ["OST_Rooms"]
  },
  {
    "RuleCode": "BCR-111",
    "RuleName": "無障礙通路配置",
    "Category": "無障礙",
    "CheckType": "Auto",
    "Parameter": "",
    "Operator": "",
    "Value": "",
    "Description": "【雙端關注】依據設計施工編第十章，自基地地面、停車位至建築物主要出入口應設置無障礙通路。無障礙坡道最大坡度不得大於 1/12 (8.33%)，高度大於 75cm 時應設置扶手與平台。",
    "Perspective": "Both",
    "LawArticle": "§167",
    "LawChapter": "第十章 無障礙建築物",
    "ApplicableCategories": ["OST_Ramps"]
  },
  {
    "RuleCode": "BCR-112",
    "RuleName": "無障礙車位設置比例",
    "Category": "無障礙",
    "CheckType": "Manual",
    "Parameter": "",
    "Operator": "",
    "Value": "",
    "Description": "【設計合規】依據設計施工編第 167-6 條，建築物應依規定車位比例與尺寸設置無障礙汽車及機車停車位，車位旁應配置黃色斜線旁通道區。",
    "Perspective": "Architect",
    "LawArticle": "§167-6",
    "LawChapter": "第十章 無障礙建築物",
    "ApplicableCategories": ["OST_Parking"]
  },
  {
    "RuleCode": "BCR-113",
    "RuleName": "無障礙盥洗室及無障礙廁所",
    "Category": "無障礙",
    "CheckType": "Manual",
    "Parameter": "",
    "Operator": "",
    "Value": "",
    "Description": "【設計合規】依據設計施工編第 167-3 條，設有男女廁所者應設置至少一處無障礙盥洗室，內部淨空間與扶手設備須符合法規標準。",
    "Perspective": "Architect",
    "LawArticle": "§167-3",
    "LawChapter": "第十章 無障礙建築物",
    "ApplicableCategories": ["OST_Rooms", "OST_PlumbingFixtures"]
  },
  {
    "RuleCode": "BCR-114",
    "RuleName": "無障礙客房設置比例",
    "Category": "無障礙",
    "CheckType": "Manual",
    "Parameter": "",
    "Operator": "",
    "Value": "",
    "Description": "【設計合規】依據設計施工編第 167-4 條，觀光旅館、一般旅館及特定供公眾使用建築物應設置符合規定比例之無障礙客房，且門口無門檻高差限制。",
    "Perspective": "Architect",
    "LawArticle": "§167-4",
    "LawChapter": "第十章 無障礙建築物",
    "ApplicableCategories": ["OST_Rooms"]
  },
  {
    "RuleCode": "BCR-115",
    "RuleName": "無障礙樓梯與扶手檢討",
    "Category": "無障礙",
    "CheckType": "Manual",
    "Parameter": "",
    "Operator": "",
    "Value": "",
    "Description": "【雙端關注】依據設計施工編第 167-2 條，無障礙樓梯構造應符合級高、級深、扶手終端水平延伸 30cm、及梯級防滑條、兩側扶手等專用規定。",
    "Perspective": "Both",
    "LawArticle": "§167-2",
    "LawChapter": "第十章 無障礙建築物",
    "ApplicableCategories": ["OST_Stairs", "OST_Railings"]
  },
  {
    "RuleCode": "BCR-116",
    "RuleName": "無障礙標誌引導設置",
    "Category": "無障礙",
    "CheckType": "Manual",
    "Parameter": "",
    "Operator": "",
    "Value": "",
    "Description": "【設計合規】依據設計施工編第 167-5 條，主要出入口、無障礙通路、盥洗室、車位等位置應配置國際無障礙專用識別藍色底白色輪椅標誌。",
    "Perspective": "Architect",
    "LawArticle": "§167-5",
    "LawChapter": "第十章 無障礙建築物",
    "ApplicableCategories": ["OST_Signage"]
  },
  {
    "RuleCode": "BCR-117",
    "RuleName": "無障礙通路寬度檢討",
    "Category": "無障礙",
    "CheckType": "Auto",
    "Parameter": "寬度",
    "Operator": ">=",
    "Value": "1300",
    "Description": "【設計合規】依據設計施工編第 167 條，無障礙通路之室內淨寬度不得小於 1.30 公尺 (1300mm)，走廊、走道應維持無障礙通暢。",
    "Perspective": "Both",
    "LawArticle": "§167",
    "LawChapter": "第十章 無障礙建築物",
    "ApplicableCategories": ["OST_Rooms"]
  },
  {
    "RuleCode": "BCR-118",
    "RuleName": "無障礙出入口淨寬",
    "Category": "無障礙",
    "CheckType": "Auto",
    "Parameter": "寬度",
    "Operator": ">=",
    "Value": "900",
    "Description": "【設計合規】依據設計施工編第 167 條，無障礙通路之出入口及門扇淨寬度不得小於 0.90 公尺 (900mm)，且不得設置門檻，或高差小於 2cm 並作斜角。",
    "Perspective": "Both",
    "LawArticle": "§167",
    "LawChapter": "第十章 無障礙建築物",
    "ApplicableCategories": ["OST_Doors"]
  },
  {
    "RuleCode": "BCR-119",
    "RuleName": "無障礙廁所空間檢討",
    "Category": "無障礙",
    "CheckType": "Auto",
    "Parameter": "寬度",
    "Operator": ">=",
    "Value": "1500",
    "Description": "【雙端關注】依據設計施工編第 170 條與無障礙設計規範，無障礙廁所盥洗室應包含直徑 1.5m 以上之迴轉空間，且寬度與深度皆不得低於 1.5m。",
    "Perspective": "Both",
    "LawArticle": "§170",
    "LawChapter": "第十章 無障礙建築物",
    "ApplicableCategories": ["OST_Rooms"]
  },
  {
    "RuleCode": "BCR-120",
    "RuleName": "停車位尺寸檢討",
    "Category": "無障礙",
    "CheckType": "SemiAuto",
    "Parameter": "寬度",
    "Operator": ">=",
    "Value": "2500",
    "Description": "【設計合規】依據設計施工編第 60 條與 167-6 條，一般汽車停車位尺寸為 2.5m x 5.5m，無障礙汽車停車位寬度應為 3.5m（含 1.5m 無障礙旁通道）。",
    "Perspective": "Both",
    "LawArticle": "§60",
    "LawChapter": "第二章 第十四節 停車空間",
    "ApplicableCategories": ["OST_Parking"]
  },
  {
    "RuleCode": "BCR-131",
    "RuleName": "昇降機設備設置檢討",
    "Category": "昇降機",
    "CheckType": "Manual",
    "Parameter": "",
    "Operator": "",
    "Value": "",
    "Description": "【設計合規】依據設計施工編第 55 條，六層以上之建築物應設置昇降機（電梯），且至少應有一部符合無障礙規範（包括點字、語音與輪椅扶手高度）。",
    "Perspective": "Architect",
    "LawArticle": "§55",
    "LawChapter": "第二章 第九節 昇降機",
    "ApplicableCategories": ["OST_Elevators"]
  },
  {
    "RuleCode": "BCR-132",
    "RuleName": "垃圾集中場設置檢討",
    "Category": "其他",
    "CheckType": "Manual",
    "Parameter": "",
    "Operator": "",
    "Value": "",
    "Description": "【設計合規】依據設計施工編第 55 條規定之建築用途及規模，應留設專用之垃圾集中儲存及分類收集空間，並配置清洗水龍頭與排水設備。",
    "Perspective": "Architect",
    "LawArticle": "§55",
    "LawChapter": "第二章 第九節 其他",
    "ApplicableCategories": ["OST_Rooms"]
  },
  {
    "RuleCode": "BCR-141",
    "RuleName": "雨水貯留與中水道利用",
    "Category": "其他",
    "CheckType": "Manual",
    "Parameter": "",
    "Operator": "",
    "Value": "",
    "Description": "【設計合規】依據設計施工編第 298 條，新建建築物（一定規模以上）應依規定設置雨水貯留利用設備（蓄水池）或中水道利用系統，回收灌溉廁所用水。",
    "Perspective": "Architect",
    "LawArticle": "§298",
    "LawChapter": "第十五章 綠色建築",
    "ApplicableCategories": ["OST_ProjectInformation"]
  },
  {
    "RuleCode": "BCR-142",
    "RuleName": "雨水流出抑制與排洪檢討",
    "Category": "其他",
    "CheckType": "Manual",
    "Parameter": "",
    "Operator": "",
    "Value": "",
    "Description": "【設計合規】依據設計施工編第 298 條，開發案應設置雨水蓄留與流出抑制設施（防洪調節池），限制排洪峰值，預防都市暴雨溢流負荷。",
    "Perspective": "Architect",
    "LawArticle": "§298",
    "LawChapter": "第十五章 綠色建築",
    "ApplicableCategories": ["OST_ProjectInformation"]
  }
]
